{
  "concept": {
    "title": "Tic Tac Toe: Galactic Conquest",
    "description": "A strategic topdown 2D Tic Tac Toe game where players battle across a cosmic grid, aiming to achieve galactic domination by conquering sectors.",
    "genre": "Puzzle",
    "theme": "Retro Sci-Fi, abstract cosmic grid",
    "objective": "To win a set number of Tic Tac Toe matches consecutively or reach a target score by conquering planets on a larger cosmic map.",
    "mechanics": [
      "Placing 'X' or 'O' marks on a 3x3 grid to form a line (horizontally, vertically, or diagonally).",
      "Navigating a topdown star map with multiple interconnected Tic Tac Toe 'planets'.",
      "Winning a Tic Tac Toe match on a planet claims it for your faction."
    ],
    "player_abilities": [
      "Standard 'X' or 'O' placement.",
      "Strategic 'warp' to different planets on the star map.",
      "Limited-use 'gravity well' to temporarily disrupt opponent's placement (visualized as a brief area denial on the grid)."
    ],
    "enemies": [
      {
        "name": "Nebula Nuisance",
        "behavior": "Plays a basic, predictable Tic Tac Toe strategy.  Focuses on blocking rather than offense.",
        "difficulty": "easy"
      },
      {
        "name": "Comet Crusader",
        "behavior": "Aggressively attempts to win by prioritizing offensive moves, sometimes leaving itself open to counter-attacks.",
        "difficulty": "medium"
      },
      {
        "name": "Black Hole Baron",
        "behavior": "Employs advanced AI, analyzing multiple moves ahead and employing complex defensive and offensive strategies.",
        "difficulty": "hard"
      }
    ],
    "powerups": [
      {
        "name": "Quantum Shift",
        "effect": "Allows the player to swap the positions of two of their existing marks on the current Tic Tac Toe grid."
      },
      {
        "name": "Nebula Shield",
        "effect": "Protects the player's next placed mark from being erased or overwritten by the opponent for one turn."
      }
    ],
    "level_progression": "Players progress by conquering planets on the star map. Each conquered planet may unlock new challenges, harder AI opponents, or new powerups. The ultimate goal is to conquer a specific number of planets or a central 'Galactic Core' planet.",
    "scoring_system": "Points are awarded for each Tic Tac Toe win. Bonus points are awarded for winning matches quickly, achieving perfect wins (no opponent moves), or winning multiple games in a row. Conquering planets adds to a cumulative galactic influence score.",
    "visual_style": "Retro sci-fi with a clean, minimalist aesthetic.  Bright, glowing 'X' and 'O' markers against a dark, star-filled background.  Planets on the map are stylized celestial bodies with subtle animations.  UI elements are reminiscent of old computer terminals.",
    "sound_theme": "Synthwave soundtrack with a focus on atmospheric pads, pulsing basslines, and electronic percussion.  Satisfying 'zap' and 'thump' sound effects for placing marks, and a triumphant fanfare for winning.  Subtle ambient hums for the cosmic background."
  },
  "level_design": {
    "level_number": 1,
    "name": "Proxima Centauri Outpost",
    "description": "Your first mission: secure the Proxima Centauri system. A small outpost needs to be cleared of lingering pirate activity and claimed for the Galactic Alliance. Beware of their primitive defenses and patrol routes.",
    "size": {
      "width": 800,
      "height": 600
    },
    "spawn_points": [
      {
        "x": 100,
        "y": 100,
        "type": "player"
      },
      {
        "x": 400,
        "y": 300,
        "type": "enemy"
      }
    ],
    "obstacles": [
      {
        "x": 250,
        "y": 150,
        "width": 70,
        "height": 70,
        "type": "asteroid_field"
      },
      {
        "x": 550,
        "y": 200,
        "width": 40,
        "height": 40,
        "type": "derelict_ship"
      },
      {
        "x": 180,
        "y": 450,
        "width": 50,
        "height": 50,
        "type": "asteroid_field"
      }
    ],
    "powerups": [
      {
        "x": 300,
        "y": 500,
        "type": "shield_boost"
      },
      {
        "x": 650,
        "y": 100,
        "type": "ammo_refill"
      }
    ],
    "enemies": [
      {
        "x": 350,
        "y": 250,
        "type": "basic_pirate",
        "patrol_path": [
          [
            350,
            250
          ],
          [
            400,
            250
          ],
          [
            400,
            300
          ],
          [
            350,
            300
          ]
        ]
      },
      {
        "x": 150,
        "y": 450,
        "type": "basic_pirate",
        "patrol_path": [
          [
            150,
            450
          ],
          [
            200,
            450
          ]
        ]
      },
      {
        "x": 600,
        "y": 400,
        "type": "turret",
        "patrol_path": []
      }
    ],
    "objectives": [
      {
        "type": "defeat",
        "target": "basic_pirate",
        "count": 2
      },
      {
        "type": "destroy",
        "target": "turret",
        "count": 1
      },
      {
        "type": "claim_planet",
        "target": "Proxima_Centauri_I",
        "count": 1
      }
    ],
    "difficulty": "easy",
    "time_limit": 180
  },
  "assets": {
    "player": "A simple, glowing blue triangular ship, slightly elongated.",
    "enemies": {
      "basic": "A small, pulsing red circle.",
      "aggressive": "A sharp, angular, glowing purple star shape."
    },
    "powerups": {
      "health": "A bright green, stylized plus symbol enclosed in a circle.",
      "speed": "A yellow, streaking arrow pointing forward."
    },
    "obstacles": {
      "wall": "A solid, dark grey rectangular block.",
      "rock": "An irregular, dark brown blob with a slightly rough texture."
    },
    "background": "A deep black expanse filled with small, twinkling white dots representing stars. Occasional faint, swirling nebulae in shades of blue and purple.",
    "ui_elements": {
      "score": "Green, blocky digital font displaying the current score, similar to an old calculator.",
      "health_bar": "A horizontal bar, filling from red to green, with segmented lines to indicate health levels. Appears within a simple, outlined rectangle."
    }
  },
  "created_at": "2025-10-19T06:54:18.145474",
  "theme": "a simple tic tac toe game"
}